psychopy_legacy_mic/__init__.py
psychopy_legacy_mic/microphone.py
psychopy_legacy_mic-0.0.1.post1.dist-info/LICENSE
psychopy_legacy_mic-0.0.1.post1.dist-info/METADATA
psychopy_legacy_mic-0.0.1.post1.dist-info/WHEEL
psychopy_legacy_mic-0.0.1.post1.dist-info/top_level.txt
psychopy_legacy_mic-0.0.1.post1.dist-info/RECORD
